sysutil/__init__.py
sysutil/base_path.py
sysutil-0.5.2.dist-info/METADATA
sysutil-0.5.2.dist-info/WHEEL
sysutil-0.5.2.dist-info/top_level.txt
sysutil-0.5.2.dist-info/RECORD
