Metadata-Version: 1.1
Name: sysutil
Version: 0.5.2
Summary: A lib for common methods used in project
Home-page: https://github.com/vmartian/sysutil.git
Author: Vivekanand Pandey
Author-email: vivekanandpandey98@gmail.com
License: UNKNOWN
Download-URL: https://github.com/vmartian/sysutil/archive/master.zip
Keywords: common,system,library
Platform: UNKNOWN
